CMakeLists.txt
LICENSE.md
MANIFEST.in
README.md
howto.txt
setup.py
core/CMakeLists.txt
core/apriltag.c
core/apriltag.h
core/apriltag_demo.c
core/apriltag_family.c
core/apriltag_family.h
core/apriltag_quad_thresh.c
core/g2d.c
core/g2d.h
core/tag16h5.c
core/tag16h5.h
core/tag25h7.c
core/tag25h7.h
core/tag25h9.c
core/tag25h9.h
core/tag36artoolkit.c
core/tag36artoolkit.h
core/tag36h10.c
core/tag36h10.h
core/tag36h11.c
core/tag36h11.h
core/common/assert_with_unused.h
core/common/getopt.c
core/common/getopt.h
core/common/homography.c
core/common/homography.h
core/common/image_f32.c
core/common/image_f32.h
core/common/image_u32.c
core/common/image_u32.h
core/common/image_u8.c
core/common/image_u8.h
core/common/matd.c
core/common/matd.h
core/common/math_util.h
core/common/pnm.c
core/common/pnm.h
core/common/postscript_utils.h
core/common/string_util.c
core/common/string_util.h
core/common/svd22.c
core/common/svd22.h
core/common/thash_impl.h
core/common/time_util.c
core/common/time_util.h
core/common/timeprofile.h
core/common/unionfind.c
core/common/unionfind.h
core/common/workerpool.c
core/common/workerpool.h
core/common/zarray.c
core/common/zarray.h
core/common/zhash.c
core/common/zhash.h
core/common/zmaxheap.c
core/common/zmaxheap.h
core/contrib/apriltag_quad_contour.c
core/contrib/apriltag_quad_contour.h
core/contrib/apriltag_vis.c
core/contrib/apriltag_vis.h
core/contrib/box.c
core/contrib/box.h
core/contrib/contour.c
core/contrib/contour.h
core/contrib/contour_test.c
core/contrib/lm.c
core/contrib/lm.h
core/contrib/lm_test.cpp
core/contrib/maketags.c
core/contrib/pdf_test.cpp
core/contrib/pdfutil.c
core/contrib/pdfutil.h
core/contrib/pose.c
core/contrib/pose.h
core/contrib/pose_test.c
opencv/CMakeLists.txt
opencv/apriltag_camera_demo.cpp
opencv/apriltag_opencv.cpp
opencv/apriltag_opencv.h
opencv/apriltag_opencv_demo.cpp
opencv/box_test.cpp
opencv/contour_bench.cpp
opencv/contour_line_sweep_test.cpp
python/apriltag.py
python/calibrate_camera.py
python/camtest.py
python/apriltag.egg-info/PKG-INFO
python/apriltag.egg-info/SOURCES.txt
python/apriltag.egg-info/dependency_links.txt
python/apriltag.egg-info/not-zip-safe
python/apriltag.egg-info/top_level.txt