Metadata-Version: 2.1
Name: apriltag
Version: 0.0.15
Summary: apriltag marker detection
Home-page: UNKNOWN
Author: Bernd Winkler
Author-email: bernd.winkler@ipa.fraunhofer.de
License: UNKNOWN
Platform: UNKNOWN
